zerobin/VERSION
zerobin/__init__.py
zerobin/__main__.py
zerobin/cli.py
zerobin/default_settings.py
zerobin/paste.py
zerobin/routes.py
zerobin/utils.py
zerobin/wsgi.py
zerobin/.mypy_cache/.gitignore
zerobin/.mypy_cache/3.7/@plugins_snapshot.json
zerobin/.mypy_cache/3.7/_ast.data.json
zerobin/.mypy_cache/3.7/_ast.meta.json
zerobin/.mypy_cache/3.7/_importlib_modulespec.data.json
zerobin/.mypy_cache/3.7/_importlib_modulespec.meta.json
zerobin/.mypy_cache/3.7/_random.data.json
zerobin/.mypy_cache/3.7/_random.meta.json
zerobin/.mypy_cache/3.7/abc.data.json
zerobin/.mypy_cache/3.7/abc.meta.json
zerobin/.mypy_cache/3.7/ast.data.json
zerobin/.mypy_cache/3.7/ast.meta.json
zerobin/.mypy_cache/3.7/base64.data.json
zerobin/.mypy_cache/3.7/base64.meta.json
zerobin/.mypy_cache/3.7/builtins.data.json
zerobin/.mypy_cache/3.7/builtins.meta.json
zerobin/.mypy_cache/3.7/codecs.data.json
zerobin/.mypy_cache/3.7/codecs.meta.json
zerobin/.mypy_cache/3.7/datetime.data.json
zerobin/.mypy_cache/3.7/datetime.meta.json
zerobin/.mypy_cache/3.7/genericpath.data.json
zerobin/.mypy_cache/3.7/genericpath.meta.json
zerobin/.mypy_cache/3.7/hashlib.data.json
zerobin/.mypy_cache/3.7/hashlib.meta.json
zerobin/.mypy_cache/3.7/hmac.data.json
zerobin/.mypy_cache/3.7/hmac.meta.json
zerobin/.mypy_cache/3.7/io.data.json
zerobin/.mypy_cache/3.7/io.meta.json
zerobin/.mypy_cache/3.7/mmap.data.json
zerobin/.mypy_cache/3.7/mmap.meta.json
zerobin/.mypy_cache/3.7/pathlib.data.json
zerobin/.mypy_cache/3.7/pathlib.meta.json
zerobin/.mypy_cache/3.7/posix.data.json
zerobin/.mypy_cache/3.7/posix.meta.json
zerobin/.mypy_cache/3.7/random.data.json
zerobin/.mypy_cache/3.7/random.meta.json
zerobin/.mypy_cache/3.7/runpy.data.json
zerobin/.mypy_cache/3.7/runpy.meta.json
zerobin/.mypy_cache/3.7/secrets.data.json
zerobin/.mypy_cache/3.7/secrets.meta.json
zerobin/.mypy_cache/3.7/sys.data.json
zerobin/.mypy_cache/3.7/sys.meta.json
zerobin/.mypy_cache/3.7/time.data.json
zerobin/.mypy_cache/3.7/time.meta.json
zerobin-1.0.5.dist-info/LICENCE
zerobin-1.0.5.dist-info/METADATA
zerobin-1.0.5.dist-info/WHEEL
zerobin-1.0.5.dist-info/entry_points.txt
zerobin-1.0.5.dist-info/top_level.txt
zerobin-1.0.5.dist-info/RECORD
