Metadata-Version: 2.1
Name: zerobin
Version: 1.0.5
Summary: A client side encrypted pastebin
Home-page: https://0bin.net
Author: Sam et Max
Author-email: lesametlemax@gmail.com
License: UNKNOWN
Keywords: pastebin,encryption
Platform: UNKNOWN
Requires-Dist: clize (==4.1.1)
Requires-Dist: lockfile (==0.12.2)
Requires-Dist: bottle (==0.12.18)
Requires-Dist: Beaker (==1.11.0)
Requires-Dist: Paste (==3.4.3)
Requires-Dist: appdirs (==1.4.4)
Requires-Dist: bleach (==3.1.5)
